bluebattery/__init__.py
bluebattery/bbcharacteristics.py
bluebattery/bbdevice.py
bluebattery/cli.py
bluebattery/commands.py
bluebattery/conversions.py
bluebattery/frametypes.py
bluebattery/ha_sensors.py
bluebattery/output/log.py
bluebattery/output/mqtt.py
bluebattery_py-1.2.0.dist-info/METADATA
bluebattery_py-1.2.0.dist-info/WHEEL
bluebattery_py-1.2.0.dist-info/entry_points.txt
bluebattery_py-1.2.0.dist-info/RECORD
