Metadata-Version: 2.4
Name: bluebattery-py
Version: 1.2.0
Summary: 
Author: Daniel Fett
Author-email: fett@danielfett.de
Requires-Python: >=3.7,<4.0
Classifier: Programming Language :: Python :: 3
Classifier: Programming Language :: Python :: 3.7
Classifier: Programming Language :: Python :: 3.8
Classifier: Programming Language :: Python :: 3.9
Classifier: Programming Language :: Python :: 3.10
Classifier: Programming Language :: Python :: 3.11
Classifier: Programming Language :: Python :: 3.12
Classifier: Programming Language :: Python :: 3.13
Classifier: Programming Language :: Python :: 3.14
Requires-Dist: bleak (>=0.19.5,<0.20.0)
Requires-Dist: coloredlogs (>=15.0.1,<16.0.0)
Requires-Dist: hummable (>=0.1.0,<0.2.0)
Requires-Dist: paho-mqtt (>=1.6.1,<2.0.0)
Requires-Dist: py-flags (>=1.1.4,<2.0.0)
